oresmen/__init__.py
oresmen/_version.py
oresmen/main.py
oresmen-0.1.2.dist-info/LICENSE
oresmen-0.1.2.dist-info/METADATA
oresmen-0.1.2.dist-info/WHEEL
oresmen-0.1.2.dist-info/RECORD
