Metadata-Version: 2.3
Name: oresmen
Version: 0.1.2
Summary: A module for generating Oresme numbers (harmonic series partial sums)
License: MIT
Author: Mehmet Keçeci
Author-email: mkececi@yaani.com
Requires-Python: >=3.11,<4.0
Classifier: License :: OSI Approved :: MIT License
Classifier: Programming Language :: Python :: 3
Classifier: Programming Language :: Python :: 3.11
Classifier: Programming Language :: Python :: 3.12
Classifier: Programming Language :: Python :: 3.13
Requires-Dist: numpy (>=2.3.2,<3.0.0)
